asyncio_backport/__init__.py
asyncio_backport/_impl.py
asyncio_backport/py.typed
asyncio_backport-0.1.1.dist-info/WHEEL
asyncio_backport-0.1.1.dist-info/METADATA
asyncio_backport-0.1.1.dist-info/RECORD
